sopel_modules.tenor-0.2.0-py3.9-nspkg.pth
sopel_modules/tenor/__init__.py
sopel_modules/tenor/tenor.py
tests/__init__.py
tests/test_tenor.py
sopel_modules.tenor-0.2.0.dist-info/COPYING
sopel_modules.tenor-0.2.0.dist-info/METADATA
sopel_modules.tenor-0.2.0.dist-info/WHEEL
sopel_modules.tenor-0.2.0.dist-info/namespace_packages.txt
sopel_modules.tenor-0.2.0.dist-info/top_level.txt
sopel_modules.tenor-0.2.0.dist-info/RECORD
