Metadata-Version: 2.1
Name: sopel-modules.tenor
Version: 0.2.0
Summary: A sopel plugin for tenor gifs
Home-page: https://github.com/shanedabes/sopel-tenor
Author: Shane Donohoe
Author-email: shane@donohoe.cc
License: Eiffel Forum License, version 2
Platform: UNKNOWN
License-File: COPYING
Requires-Dist: sopel (<8,>=6.0)
